CHANGES.txt
LICENSE.txt
MANIFEST.in
README
setup.py
VFClust.egg-info/PKG-INFO
VFClust.egg-info/SOURCES.txt
VFClust.egg-info/dependency_links.txt
VFClust.egg-info/entry_points.txt
VFClust.egg-info/top_level.txt
docs/_build/html/.buildinfo
docs/_build/html/genindex.html
docs/_build/html/index.html
docs/_build/html/modules.html
docs/_build/html/objects.inv
docs/_build/html/py-modindex.html
docs/_build/html/search.html
docs/_build/html/searchindex.js
docs/_build/html/vfclust.html
docs/_build/html/_sources/index.txt
docs/_build/html/_sources/modules.txt
docs/_build/html/_sources/vfclust.txt
docs/_build/html/_static/ajax-loader.gif
docs/_build/html/_static/basic.css
docs/_build/html/_static/comment-bright.png
docs/_build/html/_static/comment-close.png
docs/_build/html/_static/comment.png
docs/_build/html/_static/default.css
docs/_build/html/_static/doctools.js
docs/_build/html/_static/down-pressed.png
docs/_build/html/_static/down.png
docs/_build/html/_static/file.png
docs/_build/html/_static/jquery.js
docs/_build/html/_static/minus.png
docs/_build/html/_static/plus.png
docs/_build/html/_static/pygments.css
docs/_build/html/_static/searchtools.js
docs/_build/html/_static/sidebar.js
docs/_build/html/_static/underscore.js
docs/_build/html/_static/up-pressed.png
docs/_build/html/_static/up.png
docs/_build/html/_static/websupport.js
vfclust/Makefile
vfclust/TextGridParser.py
vfclust/TextGridParser.pyc
vfclust/__init__.py
vfclust/__init__.pyc
vfclust/vfclust.py
vfclust/vfclust.pyc
vfclust/data/animals_names.dat
vfclust/data/animals_names_raw.dat
vfclust/data/cmudict.0.7a.tree
vfclust/data/modified_cmudict.dat
vfclust/data/t2pin.tmp
vfclust/data/EOWL/EOWL Version Notes.txt
vfclust/data/EOWL/The English Open Word List.pdf
vfclust/data/EOWL/english_words.txt
vfclust/data/animals_term_vector_dictionaries/term_vectors_dict91.dat
vfclust/data/animals_term_vector_dictionaries/term_vectors_dict91_cpickle.dat
vfclust/data/nltk_data/corpora/wordnet.zip
vfclust/data/nltk_data/corpora/wordnet/adj.exc
vfclust/data/nltk_data/corpora/wordnet/adv.exc
vfclust/data/nltk_data/corpora/wordnet/cntlist.rev
