Metadata-Version: 1.1
Name: VFClust
Version: 0.1.1
Summary: Clustering of Verbal Fluency responses.
Home-page: https://github.com/speechinformaticslab/vfclust
Author: Thomas Christie, James Ryan, Kyle Marek-Spartz and Serguei Pakhomov
Author-email: tchristie@umn.edu
License: Apache License, Version 2.0
Keywords: bioinformatics speech linguistics
Platform: UNKNOWN
Classifier: Development Status :: 3 - Alpha
Classifier: Intended Audience :: Developers
Classifier: Intended Audience :: Healthcare Industry
Classifier: Intended Audience :: Science/Research
Classifier: Topic :: Multimedia :: Sound/Audio :: Speech
Classifier: Topic :: Scientific/Engineering :: Bio-Informatics
Classifier: Topic :: Scientific/Engineering :: Medical Science Apps.
Classifier: Topic :: Software Development :: Libraries
Classifier: Topic :: Text Processing :: Linguistic
Classifier: License :: OSI Approved :: Apache Software License
Classifier: Programming Language :: Python :: 2.7
Classifier: Programming Language :: C
